example_pkg/__init__.py
pkg_1_lyh-0.0.1.dist-info/LICENSE
pkg_1_lyh-0.0.1.dist-info/METADATA
pkg_1_lyh-0.0.1.dist-info/WHEEL
pkg_1_lyh-0.0.1.dist-info/top_level.txt
pkg_1_lyh-0.0.1.dist-info/RECORD
