Metadata-Version: 2.1
Name: pkg-1-lyh
Version: 0.0.1
Summary: A small example package
Home-page: https://github.com/pypa/sampleproject
Author: Yihan Lin
Author-email: 22373442@buaa.edu.cn
Classifier: Programming Language :: Python :: 3
Classifier: License :: OSI Approved :: MIT License
Classifier: Operating System :: OS Independent
License-File: LICENSE
Requires-Dist: numpy
